xarray_grass/__init__.py
xarray_grass/coord_utils.py
xarray_grass/grass_backend_array.py
xarray_grass/grass_interface.py
xarray_grass/to_grass.py
xarray_grass/xarray_grass.py
xarray_grass-0.4.0.dist-info/licenses/LICENSE
xarray_grass-0.4.0.dist-info/METADATA
xarray_grass-0.4.0.dist-info/WHEEL
xarray_grass-0.4.0.dist-info/entry_points.txt
xarray_grass-0.4.0.dist-info/top_level.txt
xarray_grass-0.4.0.dist-info/RECORD
