Metadata-Version: 2.4
Name: xarray-grass
Version: 0.4.0
Summary: An Xarray backend for GRASS raster data.
Author-email: Laurent Courty <lrntct@gmail.com>
License-Expression: GPL-2.0-or-later
Project-URL: Repository, https://github.com/lrntct/xarray-grass
Project-URL: Issues, https://github.com/lrntct/xarray-grass/issues
Classifier: Development Status :: 3 - Alpha
Classifier: Operating System :: OS Independent
Classifier: Intended Audience :: Science/Research
Classifier: Programming Language :: Python
Classifier: Programming Language :: Python :: 3
Classifier: Programming Language :: Python :: 3.11
Classifier: Programming Language :: Python :: 3.12
Classifier: Programming Language :: Python :: 3.13
Classifier: Programming Language :: Python :: 3.14
Classifier: Topic :: Scientific/Engineering
Requires-Python: >=3.11
License-File: LICENSE
Requires-Dist: numpy>=2.2.5
Requires-Dist: pyproj>=3.7.1
Requires-Dist: pandas>=2.2.3
Requires-Dist: xarray>=2025.4.0
Dynamic: license-file
